sortcraft/__init__.py
sortcraft/py.typed
sortcraft/utils.py
sortcraft/algorithms/bitonic.py
sortcraft/algorithms/bogo.py
sortcraft/algorithms/bubble.py
sortcraft/algorithms/bucket.py
sortcraft/algorithms/cocktail.py
sortcraft/algorithms/comb.py
sortcraft/algorithms/counting.py
sortcraft/algorithms/cycle.py
sortcraft/algorithms/flash.py
sortcraft/algorithms/gnome.py
sortcraft/algorithms/heap.py
sortcraft/algorithms/insertion.py
sortcraft/algorithms/merge.py
sortcraft/algorithms/nodes.py
sortcraft/algorithms/odd_even.py
sortcraft/algorithms/pancake.py
sortcraft/algorithms/pigeonhole.py
sortcraft/algorithms/quick.py
sortcraft/algorithms/radix.py
sortcraft/algorithms/selection.py
sortcraft/algorithms/shell.py
sortcraft/algorithms/stooge.py
sortcraft/algorithms/timsort.py
sortcraft-1.0.0.dist-info/licenses/LICENSE
sortcraft-1.0.0.dist-info/METADATA
sortcraft-1.0.0.dist-info/WHEEL
sortcraft-1.0.0.dist-info/top_level.txt
sortcraft-1.0.0.dist-info/RECORD
