Metadata-Version: 2.4
Name: sortcraft
Version: 1.0.0
Summary: A collection of classic and practical sorting algorithms
Author-email: Arijit Kumar Roy <arijitkroy16@gmail.com>
License: MIT License
Project-URL: Homepage, https://github.com/arijitkroy/sortcraft
Project-URL: Bug Tracker, https://github.com/arijitkroy/sortcraft/issues
Keywords: sorting,algorithms,education,cs
Classifier: Programming Language :: Python :: 3
Classifier: Programming Language :: Python :: 3 :: Only
Classifier: License :: OSI Approved :: MIT License
Classifier: Intended Audience :: Developers
Classifier: Topic :: Software Development :: Libraries
Classifier: Typing :: Typed
Requires-Python: >=3.8
License-File: LICENSE
Dynamic: license-file
